{
  "$comment": "GENERATED by github.com/lnorton89/golc/internal/contracts. DO NOT EDIT. Schema: golc-project.",
  "$id": "https://github.com/lnorton89/golc/internal/contracts/root-index-schema",
  "$schema": "https://json-schema.org/draft/2020-12/schema",
  "additionalProperties": false,
  "properties": {
    "concerns": {
      "description": "Ordered concern id/path pairs the root index discovers exactly (D-05).",
      "items": {
        "additionalProperties": false,
        "properties": {
          "id": {
            "description": "Concern id; matches exactly one internal/projectconfig ConcernSpec.ID.",
            "pattern": "^[a-z0-9][a-z0-9_-]*$",
            "type": "string"
          },
          "path": {
            "description": "Repository-relative concern file path.",
            "pattern": "^[A-Za-z0-9._-]+(/[A-Za-z0-9._-]+)*$",
            "type": "string"
          }
        },
        "required": [
          "id",
          "path"
        ],
        "type": "object"
      },
      "minItems": 1,
      "type": "array",
      "uniqueItems": true
    },
    "schema_version": {
      "description": "Supported root index schema version.",
      "enum": [
        1
      ],
      "type": "integer"
    }
  },
  "required": [
    "schema_version",
    "concerns"
  ],
  "type": "object"
}
